<ROOT>
    <SPATIAL_ENTITY objectId="0" label="plant" location="12.8449, -5.74294, 1.59086"/>
    <SPATIAL_ENTITY objectId="1" label="decoration" location="12.0798, -5.96747, 2.25736"/>
    <SPATIAL_ENTITY objectId="2" label="decoration" location="12.5851, -2.07581, 0.821703"/>
    <SPATIAL_ENTITY objectId="3" label="pot" location="10.8653, -5.94762, 0.414711"/>
    <SPATIAL_ENTITY objectId="4" label="decoration" location="10.9497, -3.59502, 0.580163"/>
    <SPATIAL_ENTITY objectId="5" label="pot" location="9.10884, -5.90116, 0.120944"/>
    <SPATIAL_ENTITY objectId="6" label="pillow" location="12.6597, -4.25329, 0.673708"/>
    <SPATIAL_ENTITY objectId="7" label="pillow" location="12.7352, -2.87737, 0.701924"/>
    <SPATIAL_ENTITY objectId="8" label="pot" location="12.4285, 1.45796, 0.189785"/>
    <SPATIAL_ENTITY objectId="9" label="pillow" location="10.8757, -1.48965, 0.425397"/>
    <SPATIAL_ENTITY objectId="10" label="decoration" location="11.627, -6.00373, 1.91573"/>
    <SPATIAL_ENTITY objectId="11" label="pillow" location="12.6538, -4.56597, 0.68936"/>
    <SPATIAL_ENTITY objectId="12" label="pillow" location="9.53663, -2.80436, 0.565094"/>
    <SPATIAL_ENTITY objectId="13" label="handrail" location="10.3678, 1.81304, 2.30017"/>
    <SPATIAL_ENTITY objectId="14" label="lamp" location="10.7914, 1.55609, 1.2942"/>
    <SPATIAL_ENTITY objectId="15" label="decoration" location="12.887, -2.01101, 0.86026"/>
    <SPATIAL_ENTITY objectId="16" label="pillow" location="12.5673, -3.14314, 0.670387"/>
    <SPATIAL_ENTITY objectId="17" label="plant" location="12.408, 1.33476, 0.58365"/>
    <SPATIAL_ENTITY objectId="18" label="vase" location="11.1525, -3.40078, 0.656159"/>
    <SPATIAL_ENTITY objectId="19" label="pillow" location="10.2777, 1.14918, 0.532098"/>
    <SPATIAL_ENTITY objectId="20" label="lamp" location="12.7758, -5.80684, 1.36802"/>
    <SPATIAL_ENTITY objectId="21" label="pot" location="13.0208, 1.30311, 0.15364"/>
    <SPATIAL_ENTITY objectId="22" label="plant" location="9.05002, -5.9116, 0.547089"/>
    <SPATIAL_ENTITY objectId="23" label="pillow" location="9.44303, -4.49887, 0.568336"/>
    <SPATIAL_ENTITY objectId="24" label="vase" location="11.3018, -3.77764, 0.765646"/>
    <SPATIAL_ENTITY objectId="25" label="window" location="13.87, 0.38817, 2.69202"/>
    <SPATIAL_ENTITY objectId="26" label="pot" location="9.71597, -5.78659, 0.377632"/>
    <SPATIAL_ENTITY objectId="27" label="lamp" location="12.8839, -1.80633, 1.25288"/>
    <SPATIAL_ENTITY objectId="28" label="mantle" location="11.2478, -6.00459, 1.69182"/>
    <SPATIAL_ENTITY objectId="29" label="table" location="9.51907, 0.770388, 0.315293"/>
    <SPATIAL_ENTITY objectId="30" label="pot" location="10.4613, -5.72704, 0.542907"/>
    <SPATIAL_ENTITY objectId="31" label="pot" location="13.2403, -5.70863, 0.263972"/>
    <SPATIAL_ENTITY objectId="32" label="sculpture" location="12.2032, 0.337736, 0.780125"/>
    <SPATIAL_ENTITY objectId="33" label="blanket" location="10.7612, -1.32265, 0.23006"/>
    <SPATIAL_ENTITY objectId="34" label="wall" location="13.8849, -4.8672, 0.373557"/>
    <SPATIAL_ENTITY objectId="35" label="ottoman" location="10.7312, 0.529697, 0.174451"/>
    <SPATIAL_ENTITY objectId="36" label="wall" location="13.857, -0.936854, 1.88371"/>
    <SPATIAL_ENTITY objectId="37" label="handrail" location="10.4627, 1.80971, 1.62551"/>
    <SPATIAL_ENTITY objectId="38" label="curtain" location="13.7931, -5.91843, 3.17322"/>
    <SPATIAL_ENTITY objectId="39" label="wall" location="13.881, -2.26492, 0.407212"/>
    <SPATIAL_ENTITY objectId="40" label="table" location="12.7069, -1.96555, 0.42074"/>
    <SPATIAL_ENTITY objectId="41" label="armchair" location="10.3311, 1.1514, 0.481579"/>
    <SPATIAL_ENTITY objectId="42" label="armchair" location="9.64944, -2.87212, 0.4016"/>
    <SPATIAL_ENTITY objectId="43" label="armchair" location="9.63742, -4.4631, 0.354701"/>
    <SPATIAL_ENTITY objectId="44" label="picture" location="11.2833, -6.06657, 2.79661"/>
    <SPATIAL_ENTITY objectId="45" label="plant" location="9.54959, -5.83286, 1.21026"/>
    <SPATIAL_ENTITY objectId="46" label="beam" location="10.5635, -0.948342, 5.65799"/>
    <SPATIAL_ENTITY objectId="47" label="curtain" location="13.887, -3.30391, 2.27398"/>
    <SPATIAL_ENTITY objectId="48" label="beam" location="10.6339, -3.56336, 5.67149"/>
    <SPATIAL_ENTITY objectId="49" label="picture" location="12.9852, 1.71066, 1.95147"/>
    <SPATIAL_ENTITY objectId="50" label="window" location="13.8674, -4.90336, 3.22717"/>
    <SPATIAL_ENTITY objectId="51" label="window" location="13.8678, -2.26621, 5.07823"/>
    <SPATIAL_ENTITY objectId="52" label="window" location="13.9676, -4.89517, 1.59482"/>
    <SPATIAL_ENTITY objectId="53" label="plant" location="13.1777, 1.26626, 1.25346"/>
    <SPATIAL_ENTITY objectId="54" label="plant" location="13.3367, -5.78036, 1.5598"/>
    <SPATIAL_ENTITY objectId="55" label="curtain" location="13.8827, 1.36202, 2.33437"/>
    <SPATIAL_ENTITY objectId="56" label="curtain" location="13.9411, -1.29544, 2.1607"/>
    <SPATIAL_ENTITY objectId="57" label="curtain" location="13.912, -0.733678, 2.13272"/>
    <SPATIAL_ENTITY objectId="58" label="window" location="13.9843, -2.28656, 3.20409"/>
    <SPATIAL_ENTITY objectId="59" label="window" location="13.894, 0.063094, 5.04693"/>
    <SPATIAL_ENTITY objectId="60" label="beam" location="11.2787, 1.4547, 5.66036"/>
    <SPATIAL_ENTITY objectId="61" label="window" location="13.8619, -4.97409, 5.15746"/>
    <SPATIAL_ENTITY objectId="62" label="curtain" location="13.8427, -3.80985, 2.27734"/>
    <SPATIAL_ENTITY objectId="63" label="coffee table" location="11.1331, -3.76956, 0.452439"/>
    <SPATIAL_ENTITY objectId="64" label="couch" location="10.9809, -1.32207, 0.300407"/>
    <SPATIAL_ENTITY objectId="65" label="window" location="13.9994, -2.2808, 1.681"/>
    <SPATIAL_ENTITY objectId="66" label="fireplace" location="11.2822, -5.88561, 1.17421"/>
    <SPATIAL_ENTITY objectId="67" label="couch" location="12.7556, -3.71601, 0.39858"/>
    <SPATIAL_ENTITY objectId="68" label="wall" location="13.7538, -2.51877, 3.06583"/>
    <SPATIAL_ENTITY objectId="69" label="ceiling" location="10.5009, -4.84937, 6.16084"/>
    <SPATIAL_ENTITY objectId="70" label="window" location="13.9659, 0.364332, 2.01303"/>
    <SPATIAL_ENTITY objectId="71" label="ceiling" location="10.7903, -2.24311, 6.15218"/>
    <SPATIAL_ENTITY objectId="72" label="ceiling" location="11.1462, 0.569891, 6.11612"/>
    <SPATIAL_ENTITY objectId="73" label="wall" location="11.4045, 1.70471, 3.04232"/>
    <SPATIAL_ENTITY objectId="74" label="unknown" location="11.3569, -2.17928, 3.04074"/>
    <SPATIAL_ENTITY objectId="75" label="wall" location="12.0211, -5.99587, 3.06732"/>
    <SPATIAL_ENTITY objectId="76" label="wall" location="9.43927, -2.23833, 2.94346"/>
    <SPATIAL_ENTITY objectId="77" label="floor" location="11.2382, -2.1592, 0.014992"/>
    <QSLINK relType="PO" figure="plant" fromId="0" ground="lamp" toId="20"/>
    <QSLINK relType="PO" figure="plant" fromId="0" ground="plant" toId="54"/>
    <QSLINK relType="NTPP" figure="plant" fromId="0" ground="unknown" toId="74"/>
    <QSLINK relType="PO" figure="plant" fromId="0" ground="wall" toId="75"/>
    <QSLINK relType="PO" figure="decoration" fromId="1" ground="decoration" toId="10"/>
    <QSLINK relType="PO" figure="decoration" fromId="1" ground="picture" toId="44"/>
    <QSLINK relType="PO" figure="decoration" fromId="1" ground="fireplace" toId="66"/>
    <QSLINK relType="NTPP" figure="decoration" fromId="1" ground="unknown" toId="74"/>
    <QSLINK relType="NTPP" figure="decoration" fromId="1" ground="wall" toId="75"/>
    <QSLINK relType="PO" figure="decoration" fromId="2" ground="lamp" toId="27"/>
    <QSLINK relType="PO" figure="decoration" fromId="2" ground="table" toId="40"/>
    <QSLINK relType="NTPP" figure="decoration" fromId="2" ground="unknown" toId="74"/>
    <QSLINK relType="PO" figure="pot" fromId="3" ground="pot" toId="30"/>
    <QSLINK relType="NTPP" figure="pot" fromId="3" ground="fireplace" toId="66"/>
    <QSLINK relType="NTPP" figure="pot" fromId="3" ground="unknown" toId="74"/>
    <QSLINK relType="NTPP" figure="pot" fromId="3" ground="wall" toId="75"/>
    <QSLINK relType="PO" figure="decoration" fromId="4" ground="vase" toId="18"/>
    <QSLINK relType="NTPP" figure="decoration" fromId="4" ground="coffee table" toId="63"/>
    <QSLINK relType="NTPP" figure="decoration" fromId="4" ground="unknown" toId="74"/>
    <QSLINK relType="PO" figure="pot" fromId="5" ground="plant" toId="22"/>
    <QSLINK relType="NTPP" figure="pot" fromId="5" ground="unknown" toId="74"/>
    <QSLINK relType="NTPP" figure="pot" fromId="5" ground="wall" toId="76"/>
    <QSLINK relType="PO" figure="pot" fromId="5" ground="floor" toId="77"/>
    <QSLINK relType="PO" figure="pillow" fromId="6" ground="pillow" toId="11"/>
    <QSLINK relType="NTPP" figure="pillow" fromId="6" ground="couch" toId="67"/>
    <QSLINK relType="NTPP" figure="pillow" fromId="6" ground="unknown" toId="74"/>
    <QSLINK relType="PO" figure="pillow" fromId="7" ground="pillow" toId="16"/>
    <QSLINK relType="PO" figure="pillow" fromId="7" ground="couch" toId="67"/>
    <QSLINK relType="NTPP" figure="pillow" fromId="7" ground="unknown" toId="74"/>
    <QSLINK relType="PO" figure="pot" fromId="8" ground="plant" toId="17"/>
    <QSLINK relType="EC" figure="pot" fromId="8" ground="pot" toId="21"/>
    <QSLINK relType="PO" figure="pot" fromId="8" ground="wall" toId="73"/>
    <QSLINK relType="NTPP" figure="pot" fromId="8" ground="unknown" toId="74"/>
    <QSLINK relType="NTPP" figure="pillow" fromId="9" ground="blanket" toId="33"/>
    <QSLINK relType="NTPP" figure="pillow" fromId="9" ground="couch" toId="64"/>
    <QSLINK relType="NTPP" figure="pillow" fromId="9" ground="unknown" toId="74"/>
    <QSLINK relType="PO" figure="decoration" fromId="10" ground="decoration" toId="1"/>
    <QSLINK relType="PO" figure="decoration" fromId="10" ground="mantle" toId="28"/>
    <QSLINK relType="PO" figure="decoration" fromId="10" ground="picture" toId="44"/>
    <QSLINK relType="NTPP" figure="decoration" fromId="10" ground="fireplace" toId="66"/>
    <QSLINK relType="NTPP" figure="decoration" fromId="10" ground="unknown" toId="74"/>
    <QSLINK relType="NTPP" figure="decoration" fromId="10" ground="wall" toId="75"/>
    <QSLINK relType="PO" figure="pillow" fromId="11" ground="pillow" toId="6"/>
    <QSLINK relType="PO" figure="pillow" fromId="11" ground="couch" toId="67"/>
    <QSLINK relType="NTPP" figure="pillow" fromId="11" ground="unknown" toId="74"/>
    <QSLINK relType="NTPP" figure="pillow" fromId="12" ground="armchair" toId="42"/>
    <QSLINK relType="NTPP" figure="pillow" fromId="12" ground="unknown" toId="74"/>
    <QSLINK relType="NTPP" figure="pillow" fromId="12" ground="wall" toId="76"/>
    <QSLINK relType="PO" figure="handrail" fromId="13" ground="handrail" toId="37"/>
    <QSLINK relType="NTPP" figure="handrail" fromId="13" ground="wall" toId="73"/>
    <QSLINK relType="NTPP" figure="handrail" fromId="13" ground="unknown" toId="74"/>
    <QSLINK relType="PO" figure="handrail" fromId="13" ground="wall" toId="76"/>
    <QSLINK relType="PO" figure="lamp" fromId="14" ground="handrail" toId="37"/>
    <QSLINK relType="PO" figure="lamp" fromId="14" ground="wall" toId="73"/>
    <QSLINK relType="NTPP" figure="lamp" fromId="14" ground="unknown" toId="74"/>
    <QSLINK relType="PO" figure="decoration" fromId="15" ground="lamp" toId="27"/>
    <QSLINK relType="PO" figure="decoration" fromId="15" ground="table" toId="40"/>
    <QSLINK relType="NTPP" figure="decoration" fromId="15" ground="unknown" toId="74"/>
    <QSLINK relType="PO" figure="pillow" fromId="16" ground="pillow" toId="7"/>
    <QSLINK relType="PO" figure="pillow" fromId="16" ground="couch" toId="67"/>
    <QSLINK relType="NTPP" figure="pillow" fromId="16" ground="unknown" toId="74"/>
    <QSLINK relType="PO" figure="plant" fromId="17" ground="pot" toId="8"/>
    <QSLINK relType="PO" figure="plant" fromId="17" ground="wall" toId="73"/>
    <QSLINK relType="NTPP" figure="plant" fromId="17" ground="unknown" toId="74"/>
    <QSLINK relType="PO" figure="vase" fromId="18" ground="decoration" toId="4"/>
    <QSLINK relType="NTPP" figure="vase" fromId="18" ground="coffee table" toId="63"/>
    <QSLINK relType="NTPP" figure="vase" fromId="18" ground="unknown" toId="74"/>
    <QSLINK relType="PO" figure="pillow" fromId="19" ground="ottoman" toId="35"/>
    <QSLINK relType="NTPP" figure="pillow" fromId="19" ground="armchair" toId="41"/>
    <QSLINK relType="NTPP" figure="pillow" fromId="19" ground="unknown" toId="74"/>
    <QSLINK relType="PO" figure="pillow" fromId="19" ground="wall" toId="76"/>
    <QSLINK relType="PO" figure="lamp" fromId="20" ground="plant" toId="0"/>
    <QSLINK relType="PO" figure="lamp" fromId="20" ground="plant" toId="54"/>
    <QSLINK relType="NTPP" figure="lamp" fromId="20" ground="unknown" toId="74"/>
    <QSLINK relType="PO" figure="lamp" fromId="20" ground="wall" toId="75"/>
    <QSLINK relType="EC" figure="pot" fromId="21" ground="pot" toId="8"/>
    <QSLINK relType="PO" figure="pot" fromId="21" ground="wall" toId="73"/>
    <QSLINK relType="NTPP" figure="pot" fromId="21" ground="unknown" toId="74"/>
    <QSLINK relType="PO" figure="plant" fromId="22" ground="pot" toId="5"/>
    <QSLINK relType="PO" figure="plant" fromId="22" ground="plant" toId="45"/>
    <QSLINK relType="NTPP" figure="plant" fromId="22" ground="unknown" toId="74"/>
    <QSLINK relType="NTPP" figure="plant" fromId="22" ground="wall" toId="76"/>
    <QSLINK relType="PO" figure="pillow" fromId="23" ground="armchair" toId="43"/>
    <QSLINK relType="NTPP" figure="pillow" fromId="23" ground="unknown" toId="74"/>
    <QSLINK relType="NTPP" figure="pillow" fromId="23" ground="wall" toId="76"/>
    <QSLINK relType="PO" figure="vase" fromId="24" ground="coffee table" toId="63"/>
    <QSLINK relType="NTPP" figure="vase" fromId="24" ground="unknown" toId="74"/>
    <QSLINK relType="PO" figure="window" fromId="25" ground="curtain" toId="55"/>
    <QSLINK relType="PO" figure="window" fromId="25" ground="curtain" toId="57"/>
    <QSLINK relType="PO" figure="window" fromId="25" ground="window" toId="59"/>
    <QSLINK relType="NTPP" figure="window" fromId="25" ground="wall" toId="68"/>
    <QSLINK relType="PO" figure="window" fromId="25" ground="window" toId="70"/>
    <QSLINK relType="NTPP" figure="window" fromId="25" ground="unknown" toId="74"/>
    <QSLINK relType="PO" figure="pot" fromId="26" ground="plant" toId="45"/>
    <QSLINK relType="PO" figure="pot" fromId="26" ground="fireplace" toId="66"/>
    <QSLINK relType="NTPP" figure="pot" fromId="26" ground="unknown" toId="74"/>
    <QSLINK relType="NTPP" figure="pot" fromId="26" ground="wall" toId="76"/>
    <QSLINK relType="PO" figure="pot" fromId="26" ground="floor" toId="77"/>
    <QSLINK relType="PO" figure="lamp" fromId="27" ground="decoration" toId="2"/>
    <QSLINK relType="PO" figure="lamp" fromId="27" ground="decoration" toId="15"/>
    <QSLINK relType="NTPP" figure="lamp" fromId="27" ground="unknown" toId="74"/>
    <QSLINK relType="PO" figure="mantle" fromId="28" ground="decoration" toId="10"/>
    <QSLINK relType="NTPP" figure="mantle" fromId="28" ground="fireplace" toId="66"/>
    <QSLINK relType="NTPP" figure="mantle" fromId="28" ground="unknown" toId="74"/>
    <QSLINK relType="NTPP" figure="mantle" fromId="28" ground="wall" toId="75"/>
    <QSLINK relType="PO" figure="table" fromId="29" ground="armchair" toId="41"/>
    <QSLINK relType="NTPP" figure="table" fromId="29" ground="unknown" toId="74"/>
    <QSLINK relType="NTPP" figure="table" fromId="29" ground="wall" toId="76"/>
    <QSLINK relType="PO" figure="table" fromId="29" ground="floor" toId="77"/>
    <QSLINK relType="PO" figure="pot" fromId="30" ground="pot" toId="3"/>
    <QSLINK relType="PO" figure="pot" fromId="30" ground="fireplace" toId="66"/>
    <QSLINK relType="NTPP" figure="pot" fromId="30" ground="unknown" toId="74"/>
    <QSLINK relType="PO" figure="pot" fromId="30" ground="wall" toId="75"/>
    <QSLINK relType="PO" figure="pot" fromId="30" ground="wall" toId="76"/>
    <QSLINK relType="PO" figure="pot" fromId="31" ground="plant" toId="54"/>
    <QSLINK relType="PO" figure="pot" fromId="31" ground="wall" toId="68"/>
    <QSLINK relType="NTPP" figure="pot" fromId="31" ground="unknown" toId="74"/>
    <QSLINK relType="PO" figure="pot" fromId="31" ground="wall" toId="75"/>
    <QSLINK relType="PO" figure="pot" fromId="31" ground="floor" toId="77"/>
    <QSLINK relType="NTPP" figure="sculpture" fromId="32" ground="unknown" toId="74"/>
    <QSLINK relType="NTTPc" figure="blanket" fromId="33" ground="pillow" toId="9"/>
    <QSLINK relType="PO" figure="blanket" fromId="33" ground="couch" toId="64"/>
    <QSLINK relType="NTPP" figure="blanket" fromId="33" ground="unknown" toId="74"/>
    <QSLINK relType="PO" figure="blanket" fromId="33" ground="wall" toId="76"/>
    <QSLINK relType="PO" figure="blanket" fromId="33" ground="floor" toId="77"/>
    <QSLINK relType="PO" figure="wall" fromId="34" ground="plant" toId="54"/>
    <QSLINK relType="PO" figure="wall" fromId="34" ground="curtain" toId="62"/>
    <QSLINK relType="PO" figure="wall" fromId="34" ground="wall" toId="68"/>
    <QSLINK relType="NTPP" figure="wall" fromId="34" ground="unknown" toId="74"/>
    <QSLINK relType="PO" figure="wall" fromId="34" ground="floor" toId="77"/>
    <QSLINK relType="PO" figure="ottoman" fromId="35" ground="pillow" toId="19"/>
    <QSLINK relType="PO" figure="ottoman" fromId="35" ground="armchair" toId="41"/>
    <QSLINK relType="NTPP" figure="ottoman" fromId="35" ground="unknown" toId="74"/>
    <QSLINK relType="PO" figure="ottoman" fromId="35" ground="wall" toId="76"/>
    <QSLINK relType="PO" figure="ottoman" fromId="35" ground="floor" toId="77"/>
    <QSLINK relType="PO" figure="wall" fromId="36" ground="curtain" toId="56"/>
    <QSLINK relType="PO" figure="wall" fromId="36" ground="curtain" toId="57"/>
    <QSLINK relType="PO" figure="wall" fromId="36" ground="wall" toId="68"/>
    <QSLINK relType="NTPP" figure="wall" fromId="36" ground="unknown" toId="74"/>
    <QSLINK relType="PO" figure="wall" fromId="36" ground="floor" toId="77"/>
    <QSLINK relType="PO" figure="handrail" fromId="37" ground="handrail" toId="13"/>
    <QSLINK relType="PO" figure="handrail" fromId="37" ground="lamp" toId="14"/>
    <QSLINK relType="PO" figure="handrail" fromId="37" ground="armchair" toId="41"/>
    <QSLINK relType="PO" figure="handrail" fromId="37" ground="wall" toId="73"/>
    <QSLINK relType="NTPP" figure="handrail" fromId="37" ground="unknown" toId="74"/>
    <QSLINK relType="PO" figure="handrail" fromId="37" ground="wall" toId="76"/>
    <QSLINK relType="PO" figure="curtain" fromId="38" ground="window" toId="50"/>
    <QSLINK relType="PO" figure="curtain" fromId="38" ground="window" toId="52"/>
    <QSLINK relType="PO" figure="curtain" fromId="38" ground="plant" toId="54"/>
    <QSLINK relType="PO" figure="curtain" fromId="38" ground="window" toId="61"/>
    <QSLINK relType="NTPP" figure="curtain" fromId="38" ground="wall" toId="68"/>
    <QSLINK relType="NTPP" figure="curtain" fromId="38" ground="unknown" toId="74"/>
    <QSLINK relType="PO" figure="curtain" fromId="38" ground="wall" toId="75"/>
    <QSLINK relType="PO" figure="wall" fromId="39" ground="curtain" toId="47"/>
    <QSLINK relType="PO" figure="wall" fromId="39" ground="curtain" toId="56"/>
    <QSLINK relType="PO" figure="wall" fromId="39" ground="window" toId="65"/>
    <QSLINK relType="PO" figure="wall" fromId="39" ground="wall" toId="68"/>
    <QSLINK relType="NTPP" figure="wall" fromId="39" ground="unknown" toId="74"/>
    <QSLINK relType="PO" figure="wall" fromId="39" ground="floor" toId="77"/>
    <QSLINK relType="PO" figure="table" fromId="40" ground="decoration" toId="2"/>
    <QSLINK relType="PO" figure="table" fromId="40" ground="decoration" toId="15"/>
    <QSLINK relType="NTPP" figure="table" fromId="40" ground="unknown" toId="74"/>
    <QSLINK relType="NTTPc" figure="armchair" fromId="41" ground="pillow" toId="19"/>
    <QSLINK relType="PO" figure="armchair" fromId="41" ground="table" toId="29"/>
    <QSLINK relType="PO" figure="armchair" fromId="41" ground="ottoman" toId="35"/>
    <QSLINK relType="PO" figure="armchair" fromId="41" ground="handrail" toId="37"/>
    <QSLINK relType="PO" figure="armchair" fromId="41" ground="wall" toId="73"/>
    <QSLINK relType="NTPP" figure="armchair" fromId="41" ground="unknown" toId="74"/>
    <QSLINK relType="PO" figure="armchair" fromId="41" ground="wall" toId="76"/>
    <QSLINK relType="PO" figure="armchair" fromId="41" ground="floor" toId="77"/>
    <QSLINK relType="NTTPc" figure="armchair" fromId="42" ground="pillow" toId="12"/>
    <QSLINK relType="NTPP" figure="armchair" fromId="42" ground="unknown" toId="74"/>
    <QSLINK relType="NTPP" figure="armchair" fromId="42" ground="wall" toId="76"/>
    <QSLINK relType="PO" figure="armchair" fromId="42" ground="floor" toId="77"/>
    <QSLINK relType="PO" figure="armchair" fromId="43" ground="pillow" toId="23"/>
    <QSLINK relType="NTPP" figure="armchair" fromId="43" ground="unknown" toId="74"/>
    <QSLINK relType="NTPP" figure="armchair" fromId="43" ground="wall" toId="76"/>
    <QSLINK relType="PO" figure="armchair" fromId="43" ground="floor" toId="77"/>
    <QSLINK relType="PO" figure="picture" fromId="44" ground="decoration" toId="1"/>
    <QSLINK relType="PO" figure="picture" fromId="44" ground="decoration" toId="10"/>
    <QSLINK relType="NTPP" figure="picture" fromId="44" ground="unknown" toId="74"/>
    <QSLINK relType="NTPP" figure="picture" fromId="44" ground="wall" toId="75"/>
    <QSLINK relType="PO" figure="plant" fromId="45" ground="plant" toId="22"/>
    <QSLINK relType="PO" figure="plant" fromId="45" ground="pot" toId="26"/>
    <QSLINK relType="NTPP" figure="plant" fromId="45" ground="unknown" toId="74"/>
    <QSLINK relType="NTPP" figure="plant" fromId="45" ground="wall" toId="76"/>
    <QSLINK relType="PO" figure="beam" fromId="46" ground="ceiling" toId="71"/>
    <QSLINK relType="PO" figure="beam" fromId="46" ground="ceiling" toId="72"/>
    <QSLINK relType="NTPP" figure="beam" fromId="46" ground="unknown" toId="74"/>
    <QSLINK relType="PO" figure="beam" fromId="46" ground="wall" toId="76"/>
    <QSLINK relType="PO" figure="curtain" fromId="47" ground="wall" toId="39"/>
    <QSLINK relType="PO" figure="curtain" fromId="47" ground="window" toId="51"/>
    <QSLINK relType="PO" figure="curtain" fromId="47" ground="window" toId="58"/>
    <QSLINK relType="PO" figure="curtain" fromId="47" ground="curtain" toId="62"/>
    <QSLINK relType="PO" figure="curtain" fromId="47" ground="window" toId="65"/>
    <QSLINK relType="NTPP" figure="curtain" fromId="47" ground="wall" toId="68"/>
    <QSLINK relType="NTPP" figure="curtain" fromId="47" ground="unknown" toId="74"/>
    <QSLINK relType="PO" figure="curtain" fromId="47" ground="floor" toId="77"/>
    <QSLINK relType="PO" figure="beam" fromId="48" ground="ceiling" toId="69"/>
    <QSLINK relType="PO" figure="beam" fromId="48" ground="ceiling" toId="71"/>
    <QSLINK relType="NTPP" figure="beam" fromId="48" ground="unknown" toId="74"/>
    <QSLINK relType="PO" figure="beam" fromId="48" ground="wall" toId="76"/>
    <QSLINK relType="PO" figure="picture" fromId="49" ground="curtain" toId="55"/>
    <QSLINK relType="NTPP" figure="picture" fromId="49" ground="wall" toId="73"/>
    <QSLINK relType="NTPP" figure="picture" fromId="49" ground="unknown" toId="74"/>
    <QSLINK relType="PO" figure="window" fromId="50" ground="curtain" toId="38"/>
    <QSLINK relType="PO" figure="window" fromId="50" ground="window" toId="52"/>
    <QSLINK relType="PO" figure="window" fromId="50" ground="plant" toId="54"/>
    <QSLINK relType="PO" figure="window" fromId="50" ground="curtain" toId="62"/>
    <QSLINK relType="NTPP" figure="window" fromId="50" ground="wall" toId="68"/>
    <QSLINK relType="NTPP" figure="window" fromId="50" ground="unknown" toId="74"/>
    <QSLINK relType="PO" figure="window" fromId="51" ground="curtain" toId="47"/>
    <QSLINK relType="PO" figure="window" fromId="51" ground="curtain" toId="56"/>
    <QSLINK relType="NTPP" figure="window" fromId="51" ground="wall" toId="68"/>
    <QSLINK relType="NTPP" figure="window" fromId="51" ground="unknown" toId="74"/>
    <QSLINK relType="PO" figure="window" fromId="52" ground="curtain" toId="38"/>
    <QSLINK relType="PO" figure="window" fromId="52" ground="window" toId="50"/>
    <QSLINK relType="PO" figure="window" fromId="52" ground="plant" toId="54"/>
    <QSLINK relType="PO" figure="window" fromId="52" ground="curtain" toId="62"/>
    <QSLINK relType="PO" figure="window" fromId="52" ground="wall" toId="68"/>
    <QSLINK relType="NTPP" figure="window" fromId="52" ground="unknown" toId="74"/>
    <QSLINK relType="PO" figure="window" fromId="52" ground="wall" toId="75"/>
    <QSLINK relType="PO" figure="plant" fromId="53" ground="wall" toId="68"/>
    <QSLINK relType="PO" figure="plant" fromId="53" ground="wall" toId="73"/>
    <QSLINK relType="NTPP" figure="plant" fromId="53" ground="unknown" toId="74"/>
    <QSLINK relType="PO" figure="plant" fromId="54" ground="plant" toId="0"/>
    <QSLINK relType="PO" figure="plant" fromId="54" ground="lamp" toId="20"/>
    <QSLINK relType="PO" figure="plant" fromId="54" ground="pot" toId="31"/>
    <QSLINK relType="PO" figure="plant" fromId="54" ground="wall" toId="34"/>
    <QSLINK relType="PO" figure="plant" fromId="54" ground="curtain" toId="38"/>
    <QSLINK relType="PO" figure="plant" fromId="54" ground="window" toId="50"/>
    <QSLINK relType="PO" figure="plant" fromId="54" ground="window" toId="52"/>
    <QSLINK relType="PO" figure="plant" fromId="54" ground="wall" toId="68"/>
    <QSLINK relType="NTPP" figure="plant" fromId="54" ground="unknown" toId="74"/>
    <QSLINK relType="PO" figure="plant" fromId="54" ground="wall" toId="75"/>
    <QSLINK relType="PO" figure="curtain" fromId="55" ground="window" toId="25"/>
    <QSLINK relType="PO" figure="curtain" fromId="55" ground="picture" toId="49"/>
    <QSLINK relType="PO" figure="curtain" fromId="55" ground="window" toId="59"/>
    <QSLINK relType="PO" figure="curtain" fromId="55" ground="wall" toId="68"/>
    <QSLINK relType="PO" figure="curtain" fromId="55" ground="window" toId="70"/>
    <QSLINK relType="PO" figure="curtain" fromId="55" ground="wall" toId="73"/>
    <QSLINK relType="NTPP" figure="curtain" fromId="55" ground="unknown" toId="74"/>
    <QSLINK relType="PO" figure="curtain" fromId="55" ground="floor" toId="77"/>
    <QSLINK relType="PO" figure="curtain" fromId="56" ground="wall" toId="36"/>
    <QSLINK relType="PO" figure="curtain" fromId="56" ground="wall" toId="39"/>
    <QSLINK relType="PO" figure="curtain" fromId="56" ground="window" toId="51"/>
    <QSLINK relType="PO" figure="curtain" fromId="56" ground="curtain" toId="57"/>
    <QSLINK relType="PO" figure="curtain" fromId="56" ground="window" toId="58"/>
    <QSLINK relType="PO" figure="curtain" fromId="56" ground="window" toId="59"/>
    <QSLINK relType="PO" figure="curtain" fromId="56" ground="window" toId="65"/>
    <QSLINK relType="PO" figure="curtain" fromId="56" ground="wall" toId="68"/>
    <QSLINK relType="NTPP" figure="curtain" fromId="56" ground="unknown" toId="74"/>
    <QSLINK relType="PO" figure="curtain" fromId="56" ground="floor" toId="77"/>
    <QSLINK relType="PO" figure="curtain" fromId="57" ground="window" toId="25"/>
    <QSLINK relType="PO" figure="curtain" fromId="57" ground="wall" toId="36"/>
    <QSLINK relType="PO" figure="curtain" fromId="57" ground="curtain" toId="56"/>
    <QSLINK relType="PO" figure="curtain" fromId="57" ground="window" toId="59"/>
    <QSLINK relType="PO" figure="curtain" fromId="57" ground="wall" toId="68"/>
    <QSLINK relType="PO" figure="curtain" fromId="57" ground="window" toId="70"/>
    <QSLINK relType="NTPP" figure="curtain" fromId="57" ground="unknown" toId="74"/>
    <QSLINK relType="PO" figure="curtain" fromId="57" ground="floor" toId="77"/>
    <QSLINK relType="PO" figure="window" fromId="58" ground="curtain" toId="47"/>
    <QSLINK relType="PO" figure="window" fromId="58" ground="curtain" toId="56"/>
    <QSLINK relType="PO" figure="window" fromId="58" ground="window" toId="65"/>
    <QSLINK relType="PO" figure="window" fromId="58" ground="wall" toId="68"/>
    <QSLINK relType="NTPP" figure="window" fromId="58" ground="unknown" toId="74"/>
    <QSLINK relType="PO" figure="window" fromId="59" ground="window" toId="25"/>
    <QSLINK relType="PO" figure="window" fromId="59" ground="curtain" toId="55"/>
    <QSLINK relType="PO" figure="window" fromId="59" ground="curtain" toId="56"/>
    <QSLINK relType="PO" figure="window" fromId="59" ground="curtain" toId="57"/>
    <QSLINK relType="NTPP" figure="window" fromId="59" ground="wall" toId="68"/>
    <QSLINK relType="NTPP" figure="window" fromId="59" ground="unknown" toId="74"/>
    <QSLINK relType="PO" figure="beam" fromId="60" ground="wall" toId="68"/>
    <QSLINK relType="PO" figure="beam" fromId="60" ground="ceiling" toId="72"/>
    <QSLINK relType="PO" figure="beam" fromId="60" ground="wall" toId="73"/>
    <QSLINK relType="NTPP" figure="beam" fromId="60" ground="unknown" toId="74"/>
    <QSLINK relType="PO" figure="beam" fromId="60" ground="wall" toId="76"/>
    <QSLINK relType="PO" figure="window" fromId="61" ground="curtain" toId="38"/>
    <QSLINK relType="PO" figure="window" fromId="61" ground="curtain" toId="62"/>
    <QSLINK relType="NTPP" figure="window" fromId="61" ground="wall" toId="68"/>
    <QSLINK relType="NTPP" figure="window" fromId="61" ground="unknown" toId="74"/>
    <QSLINK relType="PO" figure="window" fromId="61" ground="wall" toId="75"/>
    <QSLINK relType="PO" figure="curtain" fromId="62" ground="wall" toId="34"/>
    <QSLINK relType="PO" figure="curtain" fromId="62" ground="curtain" toId="47"/>
    <QSLINK relType="PO" figure="curtain" fromId="62" ground="window" toId="50"/>
    <QSLINK relType="PO" figure="curtain" fromId="62" ground="window" toId="52"/>
    <QSLINK relType="PO" figure="curtain" fromId="62" ground="window" toId="61"/>
    <QSLINK relType="PO" figure="curtain" fromId="62" ground="wall" toId="68"/>
    <QSLINK relType="NTPP" figure="curtain" fromId="62" ground="unknown" toId="74"/>
    <QSLINK relType="PO" figure="curtain" fromId="62" ground="floor" toId="77"/>
    <QSLINK relType="NTTPc" figure="coffee table" fromId="63" ground="decoration" toId="4"/>
    <QSLINK relType="NTTPc" figure="coffee table" fromId="63" ground="vase" toId="18"/>
    <QSLINK relType="PO" figure="coffee table" fromId="63" ground="vase" toId="24"/>
    <QSLINK relType="NTPP" figure="coffee table" fromId="63" ground="unknown" toId="74"/>
    <QSLINK relType="PO" figure="coffee table" fromId="63" ground="floor" toId="77"/>
    <QSLINK relType="NTTPc" figure="couch" fromId="64" ground="pillow" toId="9"/>
    <QSLINK relType="PO" figure="couch" fromId="64" ground="blanket" toId="33"/>
    <QSLINK relType="PO" figure="couch" fromId="64" ground="unknown" toId="74"/>
    <QSLINK relType="PO" figure="couch" fromId="64" ground="wall" toId="76"/>
    <QSLINK relType="PO" figure="couch" fromId="64" ground="floor" toId="77"/>
    <QSLINK relType="PO" figure="window" fromId="65" ground="wall" toId="39"/>
    <QSLINK relType="PO" figure="window" fromId="65" ground="curtain" toId="47"/>
    <QSLINK relType="PO" figure="window" fromId="65" ground="curtain" toId="56"/>
    <QSLINK relType="PO" figure="window" fromId="65" ground="window" toId="58"/>
    <QSLINK relType="PO" figure="window" fromId="65" ground="wall" toId="68"/>
    <QSLINK relType="NTPP" figure="window" fromId="65" ground="unknown" toId="74"/>
    <QSLINK relType="PO" figure="fireplace" fromId="66" ground="decoration" toId="1"/>
    <QSLINK relType="NTTPc" figure="fireplace" fromId="66" ground="pot" toId="3"/>
    <QSLINK relType="NTTPc" figure="fireplace" fromId="66" ground="decoration" toId="10"/>
    <QSLINK relType="PO" figure="fireplace" fromId="66" ground="pot" toId="26"/>
    <QSLINK relType="NTTPc" figure="fireplace" fromId="66" ground="mantle" toId="28"/>
    <QSLINK relType="PO" figure="fireplace" fromId="66" ground="pot" toId="30"/>
    <QSLINK relType="NTPP" figure="fireplace" fromId="66" ground="unknown" toId="74"/>
    <QSLINK relType="PO" figure="fireplace" fromId="66" ground="wall" toId="75"/>
    <QSLINK relType="PO" figure="fireplace" fromId="66" ground="wall" toId="76"/>
    <QSLINK relType="PO" figure="fireplace" fromId="66" ground="floor" toId="77"/>
    <QSLINK relType="NTTPc" figure="couch" fromId="67" ground="pillow" toId="6"/>
    <QSLINK relType="PO" figure="couch" fromId="67" ground="pillow" toId="7"/>
    <QSLINK relType="PO" figure="couch" fromId="67" ground="pillow" toId="11"/>
    <QSLINK relType="PO" figure="couch" fromId="67" ground="pillow" toId="16"/>
    <QSLINK relType="NTPP" figure="couch" fromId="67" ground="unknown" toId="74"/>
    <QSLINK relType="PO" figure="couch" fromId="67" ground="floor" toId="77"/>
    <QSLINK relType="NTTPc" figure="wall" fromId="68" ground="window" toId="25"/>
    <QSLINK relType="PO" figure="wall" fromId="68" ground="pot" toId="31"/>
    <QSLINK relType="PO" figure="wall" fromId="68" ground="wall" toId="34"/>
    <QSLINK relType="PO" figure="wall" fromId="68" ground="wall" toId="36"/>
    <QSLINK relType="NTTPc" figure="wall" fromId="68" ground="curtain" toId="38"/>
    <QSLINK relType="PO" figure="wall" fromId="68" ground="wall" toId="39"/>
    <QSLINK relType="NTTPc" figure="wall" fromId="68" ground="curtain" toId="47"/>
    <QSLINK relType="NTTPc" figure="wall" fromId="68" ground="window" toId="50"/>
    <QSLINK relType="NTTPc" figure="wall" fromId="68" ground="window" toId="51"/>
    <QSLINK relType="PO" figure="wall" fromId="68" ground="window" toId="52"/>
    <QSLINK relType="PO" figure="wall" fromId="68" ground="plant" toId="53"/>
    <QSLINK relType="PO" figure="wall" fromId="68" ground="plant" toId="54"/>
    <QSLINK relType="PO" figure="wall" fromId="68" ground="curtain" toId="55"/>
    <QSLINK relType="PO" figure="wall" fromId="68" ground="curtain" toId="56"/>
    <QSLINK relType="PO" figure="wall" fromId="68" ground="curtain" toId="57"/>
    <QSLINK relType="PO" figure="wall" fromId="68" ground="window" toId="58"/>
    <QSLINK relType="NTTPc" figure="wall" fromId="68" ground="window" toId="59"/>
    <QSLINK relType="PO" figure="wall" fromId="68" ground="beam" toId="60"/>
    <QSLINK relType="NTTPc" figure="wall" fromId="68" ground="window" toId="61"/>
    <QSLINK relType="PO" figure="wall" fromId="68" ground="curtain" toId="62"/>
    <QSLINK relType="PO" figure="wall" fromId="68" ground="window" toId="65"/>
    <QSLINK relType="PO" figure="wall" fromId="68" ground="window" toId="70"/>
    <QSLINK relType="PO" figure="wall" fromId="68" ground="ceiling" toId="72"/>
    <QSLINK relType="NTPP" figure="wall" fromId="68" ground="unknown" toId="74"/>
    <QSLINK relType="PO" figure="wall" fromId="68" ground="wall" toId="75"/>
    <QSLINK relType="PO" figure="wall" fromId="68" ground="floor" toId="77"/>
    <QSLINK relType="PO" figure="ceiling" fromId="69" ground="beam" toId="48"/>
    <QSLINK relType="PO" figure="ceiling" fromId="69" ground="unknown" toId="74"/>
    <QSLINK relType="PO" figure="ceiling" fromId="69" ground="wall" toId="75"/>
    <QSLINK relType="PO" figure="window" fromId="70" ground="window" toId="25"/>
    <QSLINK relType="PO" figure="window" fromId="70" ground="curtain" toId="55"/>
    <QSLINK relType="PO" figure="window" fromId="70" ground="curtain" toId="57"/>
    <QSLINK relType="PO" figure="window" fromId="70" ground="wall" toId="68"/>
    <QSLINK relType="NTPP" figure="window" fromId="70" ground="unknown" toId="74"/>
    <QSLINK relType="PO" figure="window" fromId="70" ground="floor" toId="77"/>
    <QSLINK relType="PO" figure="ceiling" fromId="71" ground="beam" toId="46"/>
    <QSLINK relType="PO" figure="ceiling" fromId="71" ground="beam" toId="48"/>
    <QSLINK relType="PO" figure="ceiling" fromId="71" ground="unknown" toId="74"/>
    <QSLINK relType="PO" figure="ceiling" fromId="72" ground="beam" toId="46"/>
    <QSLINK relType="PO" figure="ceiling" fromId="72" ground="beam" toId="60"/>
    <QSLINK relType="PO" figure="ceiling" fromId="72" ground="wall" toId="68"/>
    <QSLINK relType="PO" figure="ceiling" fromId="72" ground="wall" toId="73"/>
    <QSLINK relType="PO" figure="ceiling" fromId="72" ground="unknown" toId="74"/>
    <QSLINK relType="PO" figure="wall" fromId="73" ground="pot" toId="8"/>
    <QSLINK relType="NTTPc" figure="wall" fromId="73" ground="handrail" toId="13"/>
    <QSLINK relType="PO" figure="wall" fromId="73" ground="lamp" toId="14"/>
    <QSLINK relType="PO" figure="wall" fromId="73" ground="plant" toId="17"/>
    <QSLINK relType="PO" figure="wall" fromId="73" ground="pot" toId="21"/>
    <QSLINK relType="PO" figure="wall" fromId="73" ground="handrail" toId="37"/>
    <QSLINK relType="PO" figure="wall" fromId="73" ground="armchair" toId="41"/>
    <QSLINK relType="NTTPc" figure="wall" fromId="73" ground="picture" toId="49"/>
    <QSLINK relType="PO" figure="wall" fromId="73" ground="plant" toId="53"/>
    <QSLINK relType="PO" figure="wall" fromId="73" ground="curtain" toId="55"/>
    <QSLINK relType="PO" figure="wall" fromId="73" ground="beam" toId="60"/>
    <QSLINK relType="PO" figure="wall" fromId="73" ground="ceiling" toId="72"/>
    <QSLINK relType="PO" figure="wall" fromId="73" ground="unknown" toId="74"/>
    <QSLINK relType="PO" figure="wall" fromId="73" ground="wall" toId="76"/>
    <QSLINK relType="PO" figure="wall" fromId="73" ground="floor" toId="77"/>
    <QSLINK relType="NTTPc" figure="unknown" fromId="74" ground="plant" toId="0"/>
    <QSLINK relType="NTTPc" figure="unknown" fromId="74" ground="decoration" toId="1"/>
    <QSLINK relType="NTTPc" figure="unknown" fromId="74" ground="decoration" toId="2"/>
    <QSLINK relType="NTTPc" figure="unknown" fromId="74" ground="pot" toId="3"/>
    <QSLINK relType="NTTPc" figure="unknown" fromId="74" ground="decoration" toId="4"/>
    <QSLINK relType="NTTPc" figure="unknown" fromId="74" ground="pot" toId="5"/>
    <QSLINK relType="NTTPc" figure="unknown" fromId="74" ground="pillow" toId="6"/>
    <QSLINK relType="NTTPc" figure="unknown" fromId="74" ground="pillow" toId="7"/>
    <QSLINK relType="NTTPc" figure="unknown" fromId="74" ground="pot" toId="8"/>
    <QSLINK relType="NTTPc" figure="unknown" fromId="74" ground="pillow" toId="9"/>
    <QSLINK relType="NTTPc" figure="unknown" fromId="74" ground="decoration" toId="10"/>
    <QSLINK relType="NTTPc" figure="unknown" fromId="74" ground="pillow" toId="11"/>
    <QSLINK relType="NTTPc" figure="unknown" fromId="74" ground="pillow" toId="12"/>
    <QSLINK relType="NTTPc" figure="unknown" fromId="74" ground="handrail" toId="13"/>
    <QSLINK relType="NTTPc" figure="unknown" fromId="74" ground="lamp" toId="14"/>
    <QSLINK relType="NTTPc" figure="unknown" fromId="74" ground="decoration" toId="15"/>
    <QSLINK relType="NTTPc" figure="unknown" fromId="74" ground="pillow" toId="16"/>
    <QSLINK relType="NTTPc" figure="unknown" fromId="74" ground="plant" toId="17"/>
    <QSLINK relType="NTTPc" figure="unknown" fromId="74" ground="vase" toId="18"/>
    <QSLINK relType="NTTPc" figure="unknown" fromId="74" ground="pillow" toId="19"/>
    <QSLINK relType="NTTPc" figure="unknown" fromId="74" ground="lamp" toId="20"/>
    <QSLINK relType="NTTPc" figure="unknown" fromId="74" ground="pot" toId="21"/>
    <QSLINK relType="NTTPc" figure="unknown" fromId="74" ground="plant" toId="22"/>
    <QSLINK relType="NTTPc" figure="unknown" fromId="74" ground="pillow" toId="23"/>
    <QSLINK relType="NTTPc" figure="unknown" fromId="74" ground="vase" toId="24"/>
    <QSLINK relType="NTTPc" figure="unknown" fromId="74" ground="window" toId="25"/>
    <QSLINK relType="NTTPc" figure="unknown" fromId="74" ground="pot" toId="26"/>
    <QSLINK relType="NTTPc" figure="unknown" fromId="74" ground="lamp" toId="27"/>
    <QSLINK relType="NTTPc" figure="unknown" fromId="74" ground="mantle" toId="28"/>
    <QSLINK relType="NTTPc" figure="unknown" fromId="74" ground="table" toId="29"/>
    <QSLINK relType="NTTPc" figure="unknown" fromId="74" ground="pot" toId="30"/>
    <QSLINK relType="NTTPc" figure="unknown" fromId="74" ground="pot" toId="31"/>
    <QSLINK relType="NTTPc" figure="unknown" fromId="74" ground="sculpture" toId="32"/>
    <QSLINK relType="NTTPc" figure="unknown" fromId="74" ground="blanket" toId="33"/>
    <QSLINK relType="NTTPc" figure="unknown" fromId="74" ground="wall" toId="34"/>
    <QSLINK relType="NTTPc" figure="unknown" fromId="74" ground="ottoman" toId="35"/>
    <QSLINK relType="NTTPc" figure="unknown" fromId="74" ground="wall" toId="36"/>
    <QSLINK relType="NTTPc" figure="unknown" fromId="74" ground="handrail" toId="37"/>
    <QSLINK relType="NTTPc" figure="unknown" fromId="74" ground="curtain" toId="38"/>
    <QSLINK relType="NTTPc" figure="unknown" fromId="74" ground="wall" toId="39"/>
    <QSLINK relType="NTTPc" figure="unknown" fromId="74" ground="table" toId="40"/>
    <QSLINK relType="NTTPc" figure="unknown" fromId="74" ground="armchair" toId="41"/>
    <QSLINK relType="NTTPc" figure="unknown" fromId="74" ground="armchair" toId="42"/>
    <QSLINK relType="NTTPc" figure="unknown" fromId="74" ground="armchair" toId="43"/>
    <QSLINK relType="NTTPc" figure="unknown" fromId="74" ground="picture" toId="44"/>
    <QSLINK relType="NTTPc" figure="unknown" fromId="74" ground="plant" toId="45"/>
    <QSLINK relType="NTTPc" figure="unknown" fromId="74" ground="beam" toId="46"/>
    <QSLINK relType="NTTPc" figure="unknown" fromId="74" ground="curtain" toId="47"/>
    <QSLINK relType="NTTPc" figure="unknown" fromId="74" ground="beam" toId="48"/>
    <QSLINK relType="NTTPc" figure="unknown" fromId="74" ground="picture" toId="49"/>
    <QSLINK relType="NTTPc" figure="unknown" fromId="74" ground="window" toId="50"/>
    <QSLINK relType="NTTPc" figure="unknown" fromId="74" ground="window" toId="51"/>
    <QSLINK relType="NTTPc" figure="unknown" fromId="74" ground="window" toId="52"/>
    <QSLINK relType="NTTPc" figure="unknown" fromId="74" ground="plant" toId="53"/>
    <QSLINK relType="NTTPc" figure="unknown" fromId="74" ground="plant" toId="54"/>
    <QSLINK relType="NTTPc" figure="unknown" fromId="74" ground="curtain" toId="55"/>
    <QSLINK relType="NTTPc" figure="unknown" fromId="74" ground="curtain" toId="56"/>
    <QSLINK relType="NTTPc" figure="unknown" fromId="74" ground="curtain" toId="57"/>
    <QSLINK relType="NTTPc" figure="unknown" fromId="74" ground="window" toId="58"/>
    <QSLINK relType="NTTPc" figure="unknown" fromId="74" ground="window" toId="59"/>
    <QSLINK relType="NTTPc" figure="unknown" fromId="74" ground="beam" toId="60"/>
    <QSLINK relType="NTTPc" figure="unknown" fromId="74" ground="window" toId="61"/>
    <QSLINK relType="NTTPc" figure="unknown" fromId="74" ground="curtain" toId="62"/>
    <QSLINK relType="NTTPc" figure="unknown" fromId="74" ground="coffee table" toId="63"/>
    <QSLINK relType="PO" figure="unknown" fromId="74" ground="couch" toId="64"/>
    <QSLINK relType="NTTPc" figure="unknown" fromId="74" ground="window" toId="65"/>
    <QSLINK relType="NTTPc" figure="unknown" fromId="74" ground="fireplace" toId="66"/>
    <QSLINK relType="NTTPc" figure="unknown" fromId="74" ground="couch" toId="67"/>
    <QSLINK relType="NTTPc" figure="unknown" fromId="74" ground="wall" toId="68"/>
    <QSLINK relType="PO" figure="unknown" fromId="74" ground="ceiling" toId="69"/>
    <QSLINK relType="NTTPc" figure="unknown" fromId="74" ground="window" toId="70"/>
    <QSLINK relType="PO" figure="unknown" fromId="74" ground="ceiling" toId="71"/>
    <QSLINK relType="PO" figure="unknown" fromId="74" ground="ceiling" toId="72"/>
    <QSLINK relType="PO" figure="unknown" fromId="74" ground="wall" toId="73"/>
    <QSLINK relType="NTTPc" figure="unknown" fromId="74" ground="wall" toId="75"/>
    <QSLINK relType="PO" figure="unknown" fromId="74" ground="wall" toId="76"/>
    <QSLINK relType="PO" figure="unknown" fromId="74" ground="floor" toId="77"/>
    <QSLINK relType="PO" figure="wall" fromId="75" ground="plant" toId="0"/>
    <QSLINK relType="NTTPc" figure="wall" fromId="75" ground="decoration" toId="1"/>
    <QSLINK relType="NTTPc" figure="wall" fromId="75" ground="pot" toId="3"/>
    <QSLINK relType="NTTPc" figure="wall" fromId="75" ground="decoration" toId="10"/>
    <QSLINK relType="PO" figure="wall" fromId="75" ground="lamp" toId="20"/>
    <QSLINK relType="NTTPc" figure="wall" fromId="75" ground="mantle" toId="28"/>
    <QSLINK relType="PO" figure="wall" fromId="75" ground="pot" toId="30"/>
    <QSLINK relType="PO" figure="wall" fromId="75" ground="pot" toId="31"/>
    <QSLINK relType="PO" figure="wall" fromId="75" ground="curtain" toId="38"/>
    <QSLINK relType="NTTPc" figure="wall" fromId="75" ground="picture" toId="44"/>
    <QSLINK relType="PO" figure="wall" fromId="75" ground="window" toId="52"/>
    <QSLINK relType="PO" figure="wall" fromId="75" ground="plant" toId="54"/>
    <QSLINK relType="PO" figure="wall" fromId="75" ground="window" toId="61"/>
    <QSLINK relType="PO" figure="wall" fromId="75" ground="fireplace" toId="66"/>
    <QSLINK relType="PO" figure="wall" fromId="75" ground="wall" toId="68"/>
    <QSLINK relType="PO" figure="wall" fromId="75" ground="ceiling" toId="69"/>
    <QSLINK relType="NTPP" figure="wall" fromId="75" ground="unknown" toId="74"/>
    <QSLINK relType="PO" figure="wall" fromId="75" ground="wall" toId="76"/>
    <QSLINK relType="PO" figure="wall" fromId="75" ground="floor" toId="77"/>
    <QSLINK relType="NTTPc" figure="wall" fromId="76" ground="pot" toId="5"/>
    <QSLINK relType="NTTPc" figure="wall" fromId="76" ground="pillow" toId="12"/>
    <QSLINK relType="PO" figure="wall" fromId="76" ground="handrail" toId="13"/>
    <QSLINK relType="PO" figure="wall" fromId="76" ground="pillow" toId="19"/>
    <QSLINK relType="NTTPc" figure="wall" fromId="76" ground="plant" toId="22"/>
    <QSLINK relType="NTTPc" figure="wall" fromId="76" ground="pillow" toId="23"/>
    <QSLINK relType="NTTPc" figure="wall" fromId="76" ground="pot" toId="26"/>
    <QSLINK relType="NTTPc" figure="wall" fromId="76" ground="table" toId="29"/>
    <QSLINK relType="PO" figure="wall" fromId="76" ground="pot" toId="30"/>
    <QSLINK relType="PO" figure="wall" fromId="76" ground="blanket" toId="33"/>
    <QSLINK relType="PO" figure="wall" fromId="76" ground="ottoman" toId="35"/>
    <QSLINK relType="PO" figure="wall" fromId="76" ground="handrail" toId="37"/>
    <QSLINK relType="PO" figure="wall" fromId="76" ground="armchair" toId="41"/>
    <QSLINK relType="NTTPc" figure="wall" fromId="76" ground="armchair" toId="42"/>
    <QSLINK relType="NTTPc" figure="wall" fromId="76" ground="armchair" toId="43"/>
    <QSLINK relType="NTTPc" figure="wall" fromId="76" ground="plant" toId="45"/>
    <QSLINK relType="PO" figure="wall" fromId="76" ground="beam" toId="46"/>
    <QSLINK relType="PO" figure="wall" fromId="76" ground="beam" toId="48"/>
    <QSLINK relType="PO" figure="wall" fromId="76" ground="beam" toId="60"/>
    <QSLINK relType="PO" figure="wall" fromId="76" ground="couch" toId="64"/>
    <QSLINK relType="PO" figure="wall" fromId="76" ground="fireplace" toId="66"/>
    <QSLINK relType="PO" figure="wall" fromId="76" ground="wall" toId="73"/>
    <QSLINK relType="PO" figure="wall" fromId="76" ground="unknown" toId="74"/>
    <QSLINK relType="PO" figure="wall" fromId="76" ground="wall" toId="75"/>
    <QSLINK relType="PO" figure="wall" fromId="76" ground="floor" toId="77"/>
    <QSLINK relType="PO" figure="floor" fromId="77" ground="pot" toId="5"/>
    <QSLINK relType="PO" figure="floor" fromId="77" ground="pot" toId="26"/>
    <QSLINK relType="PO" figure="floor" fromId="77" ground="table" toId="29"/>
    <QSLINK relType="PO" figure="floor" fromId="77" ground="pot" toId="31"/>
    <QSLINK relType="PO" figure="floor" fromId="77" ground="blanket" toId="33"/>
    <QSLINK relType="PO" figure="floor" fromId="77" ground="wall" toId="34"/>
    <QSLINK relType="PO" figure="floor" fromId="77" ground="ottoman" toId="35"/>
    <QSLINK relType="PO" figure="floor" fromId="77" ground="wall" toId="36"/>
    <QSLINK relType="PO" figure="floor" fromId="77" ground="wall" toId="39"/>
    <QSLINK relType="PO" figure="floor" fromId="77" ground="armchair" toId="41"/>
    <QSLINK relType="PO" figure="floor" fromId="77" ground="armchair" toId="42"/>
    <QSLINK relType="PO" figure="floor" fromId="77" ground="armchair" toId="43"/>
    <QSLINK relType="PO" figure="floor" fromId="77" ground="curtain" toId="47"/>
    <QSLINK relType="PO" figure="floor" fromId="77" ground="curtain" toId="55"/>
    <QSLINK relType="PO" figure="floor" fromId="77" ground="curtain" toId="56"/>
    <QSLINK relType="PO" figure="floor" fromId="77" ground="curtain" toId="57"/>
    <QSLINK relType="PO" figure="floor" fromId="77" ground="curtain" toId="62"/>
    <QSLINK relType="PO" figure="floor" fromId="77" ground="coffee table" toId="63"/>
    <QSLINK relType="PO" figure="floor" fromId="77" ground="couch" toId="64"/>
    <QSLINK relType="PO" figure="floor" fromId="77" ground="fireplace" toId="66"/>
    <QSLINK relType="PO" figure="floor" fromId="77" ground="couch" toId="67"/>
    <QSLINK relType="PO" figure="floor" fromId="77" ground="wall" toId="68"/>
    <QSLINK relType="PO" figure="floor" fromId="77" ground="window" toId="70"/>
    <QSLINK relType="PO" figure="floor" fromId="77" ground="wall" toId="73"/>
    <QSLINK relType="PO" figure="floor" fromId="77" ground="unknown" toId="74"/>
    <QSLINK relType="PO" figure="floor" fromId="77" ground="wall" toId="75"/>
    <QSLINK relType="PO" figure="floor" fromId="77" ground="wall" toId="76"/>
</ROOT>
